setup.py
ipodio/__init__.py
ipodio/_helpers.py
ipodio/cli.py
ipodio/console.py
ipodio/database.py
ipodio/handlers.py
ipodio/track.py
ipodio.egg-info/PKG-INFO
ipodio.egg-info/SOURCES.txt
ipodio.egg-info/dependency_links.txt
ipodio.egg-info/entry_points.txt
ipodio.egg-info/requires.txt
ipodio.egg-info/top_level.txt