Metadata-Version: 1.1
Name: ipodio
Version: 0.1.0
Summary: iPod command line managing tool
Home-page: https://github.com/jvrsantacruz/ipodio
Author: Javier Santacruz
Author-email: javier.santacruz.lc@gmail.com
License: UNKNOWN
Platform: Unix
Classifier: Environment :: Console
Classifier: Operating System :: POSIX
Classifier: Development Status :: 3 - Alpha
Classifier: Topic :: Multimedia :: Sound/Audio
Classifier: Intended Audience :: End Users/Desktop
Classifier: Programming Language :: Python
Classifier: Programming Language :: Python :: 2
Classifier: Programming Language :: Python :: 2.7
Classifier: License :: OSI Approved :: GNU General Public License v3 (GPLv3)
